Metadata-Version: 2.1
Name: PyProtWorm
Version: 0.1.2
Summary: A python package to find amino acid residues in the literature
Home-page: https://github.com/duenti/PyProtWorm
Author: Neli Fonseca
Author-email: nelijfjr@gmail.com
License: Apache License 2.0
Platform: UNKNOWN
Classifier: Development Status :: 3 - Alpha
Classifier: Intended Audience :: Science/Research
Classifier: License :: OSI Approved :: Apache Software License
Classifier: Programming Language :: Python :: 3
Classifier: Programming Language :: Python :: 3.4
Classifier: Programming Language :: Python :: 3.5
Classifier: Programming Language :: Python :: 3.6
Classifier: Programming Language :: Python :: 3.7
Classifier: Programming Language :: Python :: 3.8
